setup.py
binch.egg-info/PKG-INFO
binch.egg-info/SOURCES.txt
binch.egg-info/dependency_links.txt
binch.egg-info/entry_points.txt
binch.egg-info/requires.txt
binch.egg-info/top_level.txt
binchlib/__init__.py
binchlib/disassemble.py
binchlib/main.py
binchlib/signals.py
binchlib/statusbar.py
binchlib/view.py