Metadata-Version: 1.1
Name: binch
Version: 0.3.1
Summary: a light ELF binary patch tool
Home-page: https://github.com/tunz/binch
Author: Choongwoo Han
Author-email: cwhan.tunz@gmail.com
License: MIT
Keywords: disassemble binary patch
Platform: UNKNOWN
Classifier: Development Status :: 3 - Alpha
Classifier: Intended Audience :: Developers
Classifier: Topic :: Security
Classifier: Topic :: Software Development
Classifier: Programming Language :: Python :: 2.7
Classifier: Programming Language :: Python :: 3.4
Classifier: License :: OSI Approved :: MIT License
Classifier: Environment :: Console
Classifier: Environment :: Console :: Curses
Classifier: Operating System :: MacOS
Classifier: Operating System :: POSIX :: Linux
